pyhscore/__init__.py
pyhscore/_modidx.py
pyhscore/score.py
pyhscore-0.0.3.dist-info/licenses/LICENSE
pyhscore-0.0.3.dist-info/METADATA
pyhscore-0.0.3.dist-info/WHEEL
pyhscore-0.0.3.dist-info/entry_points.txt
pyhscore-0.0.3.dist-info/top_level.txt
pyhscore-0.0.3.dist-info/RECORD
