Metadata-Version: 2.4
Name: pyhscore
Version: 0.0.3
Summary: Compute H-scores in Python, including the canonical cell-based H-score and a pixel-wise implementation inspired by Ram et al. 2021.
Home-page: https://github.com/IntegratedPathologyUnit-ICR/pyhscore
Author: FerranC96
Author-email: ferran.cardoso@icr.ac.uk
License: Apache Software License 2.0
Keywords: nbdev jupyter notebook python pathology imaging ihc
Classifier: Development Status :: 4 - Beta
Classifier: Intended Audience :: Developers
Classifier: Natural Language :: English
Classifier: Programming Language :: Python :: 3.7
Classifier: Programming Language :: Python :: 3.8
Classifier: Programming Language :: Python :: 3.9
Classifier: Programming Language :: Python :: 3.10
Classifier: License :: OSI Approved :: Apache Software License
Requires-Python: >=3.7
License-File: LICENSE
Requires-Dist: fastcore
Requires-Dist: numpy
Requires-Dist: matplotlib
Requires-Dist: scikit-image
Provides-Extra: dev
Requires-Dist: fastcore; extra == "dev"
Requires-Dist: numpy; extra == "dev"
Requires-Dist: matplotlib; extra == "dev"
Requires-Dist: scikit-image; extra == "dev"
Requires-Dist: twine; extra == "dev"
Dynamic: author
Dynamic: author-email
Dynamic: classifier
Dynamic: description
Dynamic: description-content-type
Dynamic: home-page
Dynamic: keywords
Dynamic: license
Dynamic: license-file
Dynamic: provides-extra
Dynamic: requires-dist
Dynamic: requires-python
Dynamic: summary
